pysyncgateway/__about__.py
pysyncgateway/__init__.py
pysyncgateway/admin_client.py
pysyncgateway/client.py
pysyncgateway/data_dict.py
pysyncgateway/database.py
pysyncgateway/document.py
pysyncgateway/exceptions.py
pysyncgateway/helpers.py
pysyncgateway/query.py
pysyncgateway/resource.py
pysyncgateway/session.py
pysyncgateway/stats.py
pysyncgateway/user.py
pysyncgateway/user_client.py
pysyncgateway-2.0.0.dist-info/LICENSE
pysyncgateway-2.0.0.dist-info/METADATA
pysyncgateway-2.0.0.dist-info/WHEEL
pysyncgateway-2.0.0.dist-info/top_level.txt
pysyncgateway-2.0.0.dist-info/RECORD
