Metadata-Version: 2.1
Name: pysyncgateway
Version: 2.0.0
Summary: Library for communication with Couchbase Sync Gateway
Home-page: https://github.com/constructpm/pysyncgateway
Author: Construct Technology Ltd
Author-email: info@construct.pm
License: Apache License 2.0
Platform: UNKNOWN
Classifier: Development Status :: 5 - Production/Stable
Classifier: Intended Audience :: Developers
Classifier: License :: OSI Approved :: Apache Software License
Classifier: Programming Language :: Python :: 3
Classifier: Programming Language :: Python
Requires-Python: >=3.5, <4
Requires-Dist: requests (>=2.19.1)
Requires-Dist: six (>=1.10)
